setup.py
hastests/__init__.py
hastests/account.py
hastests/data.py
hastests/version.py
hastests.egg-info/PKG-INFO
hastests.egg-info/SOURCES.txt
hastests.egg-info/dependency_links.txt
hastests.egg-info/entry_points.txt
hastests.egg-info/not-zip-safe
hastests.egg-info/top_level.txt