Metadata-Version: 1.0
Name: hastests
Version: 0.3.0
Summary: HasTests API for Python
Home-page: http://github.com/spawngrid/hastests-python
Author: Spawngrid, Inc.
Author-email: team@spawngrid.com
License: MIT
Keywords: test tests testing hastests conceptscript json generation data TDD spawngrid
Platform: UNKNOWN
Classifier: Development Status :: 4 - Beta
Classifier: Intended Audience :: Developers
Classifier: License :: OSI Approved :: MIT License
Classifier: Topic :: Software Development :: Testing
Classifier: Topic :: Software Development :: Quality Assurance
Classifier: Programming Language :: Python :: 2.6
Classifier: Programming Language :: Python :: 2.7
Classifier: Programming Language :: Python :: 3
